Easycon/__init__.py
Easycon/connectors.py
mydbstest-0.0.1.dist-info/METADATA
mydbstest-0.0.1.dist-info/WHEEL
mydbstest-0.0.1.dist-info/top_level.txt
mydbstest-0.0.1.dist-info/RECORD
